oss/__init__.py
oss/api.py
oss/auth.py
oss/compat.py
oss/crc64_combine.py
oss/defaults.py
oss/entity.py
oss/exceptions.py
oss/headers.py
oss/http.py
oss/select_params.py
oss/select_response.py
oss/utils.py
oss/xml_utils.py
inspurcloud_oss_sdk-1.1.2.dist-info/METADATA
inspurcloud_oss_sdk-1.1.2.dist-info/WHEEL
inspurcloud_oss_sdk-1.1.2.dist-info/top_level.txt
inspurcloud_oss_sdk-1.1.2.dist-info/RECORD
